mogwai-0.7.7.dist-info/METADATA
mogwai-0.7.7.dist-info/DESCRIPTION.rst
mogwai-0.7.7.dist-info/metadata.json
mogwai-0.7.7.dist-info/WHEEL
mogwai-0.7.7.dist-info/RECORD
mogwai-0.7.7.dist-info/dependency_links.txt
mogwai-0.7.7.dist-info/top_level.txt
mogwai/__init__.py
mogwai/spec.py
mogwai/VERSION
mogwai/constants.py
mogwai/tools.py
mogwai/_compat.py
mogwai/shell.py
mogwai/exceptions.py
mogwai/connection.py
mogwai/properties/__init__.py
mogwai/properties/validators.py
mogwai/properties/base.py
mogwai/properties/properties.py
mogwai/properties/strategy.py
mogwai/gremlin/__init__.py
mogwai/gremlin/groovy.py
mogwai/gremlin/table.py
mogwai/gremlin/base.py
mogwai/tests/__init__.py
mogwai/tests/spec_tests.py
mogwai/tests/tools_tests.py
mogwai/tests/base.py
mogwai/tests/groovy_tests/__init__.py
mogwai/tests/groovy_tests/table_tests.py
mogwai/tests/groovy_tests/scanner_tests.py
mogwai/tests/groovy_tests/method_loading_tests.py
mogwai/tests/groovy_tests/groovy_test_model.groovy
mogwai/tests/models/__init__.py
mogwai/tests/models/edge_io_tests.py
mogwai/tests/models/vertex_traversals_tests.py
mogwai/tests/models/deserialize.groovy
mogwai/tests/models/vertex_queries_tests.py
mogwai/tests/models/vertex_io_tests.py
mogwai/tests/models/class_construction_tests.py
mogwai/tests/relationships_tests/__init__.py
mogwai/tests/relationships_tests/vertex_relationship_io_tests.py
mogwai/tests/relationships_tests/base_tests.py
mogwai/tests/properties_tests/__init__.py
mogwai/tests/properties_tests/strategy_tests.py
mogwai/tests/properties_tests/validators_tests.py
mogwai/tests/properties_tests/value_manager_tests.py
mogwai/tests/properties_tests/properties_tests/__init__.py
mogwai/tests/properties_tests/properties_tests/ipv4_tests.py
mogwai/tests/properties_tests/properties_tests/decimal_tests.py
mogwai/tests/properties_tests/properties_tests/string_tests.py
mogwai/tests/properties_tests/properties_tests/url_tests.py
mogwai/tests/properties_tests/properties_tests/uuid_tests.py
mogwai/tests/properties_tests/properties_tests/list_tests.py
mogwai/tests/properties_tests/properties_tests/boolean_tests.py
mogwai/tests/properties_tests/properties_tests/base_tests.py
