Metadata-Version: 2.0
Name: mogwai
Version: 0.7.7
Summary: Titan Object-Graph Mapper (OGM)
Home-page: https://bitbucket.org/wellaware/mogwai
Author: Cody Lee
Author-email: codylee@wellaware.us
License: Apache Software License 2.0
Keywords: cassandra,titan,ogm,mogwai,thunderdome
Platform: UNKNOWN
Classifier: Development Status :: 5 - Production/Stable
Classifier: Environment :: Web Environment
Classifier: Environment :: Other Environment
Classifier: Environment :: Plugins
Classifier: Intended Audience :: Developers
Classifier: License :: OSI Approved :: Apache Software License
Classifier: Operating System :: OS Independent
Classifier: Natural Language :: English
Classifier: Programming Language :: Python :: 2.7
Classifier: Programming Language :: Python :: 3.3
Classifier: Programming Language :: Python :: 3.4
Classifier: Programming Language :: Python :: Implementation
Classifier: Topic :: Database
Classifier: Topic :: Internet :: WWW/HTTP
Classifier: Topic :: Software Development :: Libraries :: Python Modules
Requires-Dist: pyparsing (>=2.0.2,<3.0.0)
Requires-Dist: rexpro (>=0.4.5,<1.0.0)
Requires-Dist: six (>=1.6.1)
Requires-Dist: argparse (>=1.2.1)
Requires-Dist: factory-boy (>=2.4.1)
Requires-Dist: pyformance (==0.2.4)
Requires-Dist: Twisted (>=13.2.0,<14.0.0)
Requires-Dist: pytz (>=2014.4)
Provides-Extra: develop
Requires-Dist: Sphinx (==1.2.2); extra == 'develop'
Requires-Dist: Twisted (>=13.2.0,<14.0.0); extra == 'develop'
Requires-Dist: blinker (==1.2); extra == 'develop'
Requires-Dist: coverage (==3.7.1); extra == 'develop'
Requires-Dist: detox (==0.9.3); extra == 'develop'
Requires-Dist: docutils (==0.11); extra == 'develop'
Requires-Dist: eventlet (>=0.14.0); extra == 'develop'
Requires-Dist: factory-boy (==2.4.1); extra == 'develop'
Requires-Dist: gevent (>=1.0.1); extra == 'develop'
Requires-Dist: msgpack-python (==0.4.2); extra == 'develop'
Requires-Dist: newrelic (==2.18.1.15); extra == 'develop'
Requires-Dist: nose (==1.3.0); extra == 'develop'
Requires-Dist: pyformance (==0.2.4); extra == 'develop'
Requires-Dist: pyparsing (==2.0.2); extra == 'develop'
Requires-Dist: pytz (==2014.4); extra == 'develop'
Requires-Dist: rexpro (>=0.4.5,<1.0.0); extra == 'develop'
Requires-Dist: six (>=1.6.1); extra == 'develop'
Requires-Dist: sphinx-rtd-theme (==0.1.6); extra == 'develop'
Requires-Dist: tox (==1.7.1); extra == 'develop'
Requires-Dist: watchdog (==0.7.1); extra == 'develop'
Requires-Dist: wercker (==0.8.3); extra == 'develop'
Requires-Dist: wheel (>=0.24.0); extra == 'develop'
Requires-Dist: pyxdg (>=0.25); extra == 'develop'
Requires-Dist: keyring (>=4.0); extra == 'develop'
Provides-Extra: docs
Requires-Dist: Sphinx (>=1.2.2); extra == 'docs'
Requires-Dist: sphinx-rtd-theme (>=0.1.6); extra == 'docs'
Requires-Dist: watchdog (>=0.7.1); extra == 'docs'
Requires-Dist: newrelic (>=2.18.1.15); extra == 'docs'
Provides-Extra: eventlet
Requires-Dist: rexpro[eventlet] (>=0.4.5); extra == 'eventlet'
Provides-Extra: gevent
Requires-Dist: rexpro[gevent] (>=0.4.5); extra == 'gevent'
Provides-Extra: newrelic
Requires-Dist: newrelic (>=2.18.1.15); extra == 'newrelic'
